{"APih/s+3gAmipyaJlEhfsg==":"untitled-2000x1335.png","93ocqNOntg8kaiszX41i/Q==":"1563346780_planets-2-122x120.jpg","eaJC5xS1xPHCrsYnSXK5zA==":"mbr-124x124.jpg","NfxLuD6B7thv+EifMECb0w==":"mbr-1920x1920.jpg","Wa/hzb7/l5RZRzCIvFhDTA==":"mbr-1920x1920.jpeg","MWUVPpVoQEVMNJOJzSLC0A==":"mbr-122x122.jpg","ccyLfxo0tzAvKbhUxn7zNA==":"barnaul-5-1380x933.jpg","hhKp4pkwUlcdegv2Ox7GUg==":"barnaul-2-1380x776.jpg","OM6hTwqMAQpTVhLcPG86xg==":"background1.jpg","UAc7kepzJPkrSn4uqTRvmw==":"background4-1.jpg","sT80Y4RCGNBrSInGgrjIuA==":"background3.jpg","zV/fTX77xNFD4TTffyXguA==":"barnaul-2-1380x776.jpeg","0TuH4BFHQnaRVPLjh6cdVg==":"barnaul-5-1380x933.jpeg","runfw9cRbfyH/5CiNSwBGg==":"asau_fk.webp","mIIbxW0r7dEZSbMPwcoYdg==":"background2.jpg","pa5Dkwo/T1qgW/t0h+fQvA==":"background5.jpg","NM0VEDvKOrotiJgP95bOkA==":"%D0%BB%D0%B5%D1%81%D0%BD%D0%BE%D0%B5_%D0%B4%D0%B5%D0%BB%D0%BE-626x348.jpeg","ajom/MEqDBYKqDQFUxHJeg==":"%D0%A0%D0%B0%D0%B7%D0%B2%D0%B5%D0%B4%D0%B5%D0%BD%D0%B8%D0%B5,%20%D0%B3%D0%B5%D0%BD%D0%B5%D1%82%D0%B8%D0%BA%D0%B0%20%D0%B8%20%D1%81%D0%B5%D0%BB%D0%B5%D0%BA%D1%86%D0%B8%D1%8F%20%D0%B6%D0%B8%D0%B2%D0%BE%D1%82%D0%BD%D1%8B%D1%85-626x419.jpeg","brYmdBekJCxV/BEV+8E8Pw==":"%D0%9A%D0%B8%D0%BD%D0%BE%D0%BB%D0%BE%D0%B3%D0%B8%D1%8F-626x447.jpeg","soDnG4U7vn+ZQCxFHhcbUA==":"%D0%A2%D0%B5%D1%85%D0%BD%D0%BE%D0%BB%D0%BE%D0%B3%D0%B8%D1%8F%20%D0%BF%D1%80%D0%BE%D0%B8%D0%B7%D0%B2%D0%BE%D0%B4%D1%81%D1%82%D0%B2%D0%B0%20%D0%BF%D1%80%D0%BE%D0%B4%D1%83%D0%BA%D1%86%D0%B8%D0%B8%20%D0%BF%D1%87%D0%B5%D0%BB%D0%BE%D0%B2%D0%BE%D0%B4%D1%81%D1%82%D0%B2%D0%B0-626x470.jpeg","rhGFqamZZAKXEjMT219yKg==":"%D0%A2%D0%B5%D1%85%D0%BD%D0%BE%D0%BB%D0%BE%D0%B3%D0%B8%D1%8F%20%D0%BF%D1%80%D0%BE%D0%B8%D0%B7%D0%B2%D0%BE%D0%B4%D1%81%D1%82%D0%B2%D0%B0%20%D0%BC%D0%BE%D0%BB%D0%BE%D0%BA%D0%B0%20%D0%B8%20%D0%BC%D1%8F%D1%81%D0%B0-626x417.jpeg","klG7avz1F5KBPIib6R4uFw==":"%D0%A1%D0%BE%D0%B2%D1%80%D0%B5%D0%BC%D0%B5%D0%BD%D0%BD%D1%8B%D0%B5%20%D1%82%D0%B5%D1%85%D0%BD%D0%BE%D0%BB%D0%BE%D0%B3%D0%B8%D0%B8%20%D0%BF%D1%80%D0%BE%D0%B8%D0%B7%D0%B2%D0%BE%D0%B4%D1%81%D1%82%D0%B2%D0%B0%20%D0%B8%20%D0%B7%D0%B0%D1%89%D0%B8%D1%82%D1%8B%20%D1%80%D0%B0%D1%81%D1%82%D0%B5%D0%BD%D0%B8%D0%B9-626x417.jpg","EkttZtv5r3LzJ0608chobg==":"%D0%A1%D0%BE%D0%B2%D1%80%D0%B5%D0%BC%D0%B5%D0%BD%D0%BD%D1%8B%D0%B5%20%D1%82%D0%B5%D1%85%D0%BD%D0%BE%D0%BB%D0%BE%D0%B3%D0%B8%D0%B8%20%D0%BF%D1%80%D0%BE%D0%B8%D0%B7%D0%B2%D0%BE%D0%B4%D1%81%D1%82%D0%B2%D0%B0%20%D0%B8%20%D0%B7%D0%B0%D1%89%D0%B8%D1%82%D1%8B%20%D1%80%D0%B0%D1%81%D1%82%D0%B5%D0%BD%D0%B8%D0%B9-626x417.jpeg","0DqUQ3dWo6s28R9rgk2Ajg==":"%D0%92%D0%B5%D1%82%D0%B5%D1%80%D0%B8%D0%BD%D0%B0%D1%80%D0%B8%D1%8F-626x417.jpeg","gyun2p9Awd+PapzQ4CiGIg==":"%D0%AD%D0%BA%D0%BE%D0%BD%D0%BE%D0%BC%D0%B8%D0%BA%D0%B0%20%D0%B8%20%D1%83%D0%BF%D1%80%D0%B0%D0%B2%D0%BB%D0%B5%D0%BD%D0%B8%D0%B5%20%D0%BF%D1%80%D0%BE%D0%B8%D0%B7%D0%B2%D0%BE%D0%B4%D1%81%D1%82%D0%B2%D0%B5%D0%BD%D0%BD%D1%8B%D0%BC%D0%B8%20%D0%BF%D1%80%D0%BE%D1%86%D0%B5%D1%81%D1%81%D0%B0%D0%BC%D0%B8%20%D0%B2%20...-626x368.jpeg","2uxtkWoXDNkC4yFNHuLUsA==":"%D0%93%D0%B8%D0%B4%D1%80%D0%BE%D0%BC%D0%B5%D0%BB%D0%B8%D0%BE%D1%80%D0%B0%D1%86%D0%B8%D1%8F-626x447.jpeg","hO+JRpsxVx4WKGBWGkbGOw==":"%D0%9F%D1%80%D0%BE%D0%B4%D1%83%D0%BA%D1%82%D1%8B%20%D0%BF%D0%B8%D1%82%D0%B0%D0%BD%D0%B8%D1%8F%20%D0%B6%D0%B8%D0%B2%D0%BE%D1%82%D0%BD%D0%BE%D0%B3%D0%BE%20%D0%BF%D1%80%D0%BE%D0%B8%D1%81%D1%85%D0%BE%D0%B6%D0%B4%D0%B5%D0%BD%D0%B8%D1%8F-626x264.jpeg","fGKH9pu6FwsJ6Jd0KyXiqw==":"%D0%98%D0%BD%D0%B6%D0%B5%D0%BD%D0%B5%D1%80%D0%BD%D1%8B%D0%B5%20%D1%81%D0%B8%D1%81%D1%82%D0%B5%D0%BC%D1%8B%20%D1%81%D0%B5%D0%BB%D1%8C%D1%81%D0%BA%D0%BE%D1%85%D0%BE%D0%B7%D1%8F%D0%B9%D1%81%D1%82%D0%B2%D0%B5%D0%BD%D0%BD%D0%BE%D0%B3%D0%BE%20%D0%B2%D0%BE%D0%B4%D0%BE%D1%81%D0%BD%D0%B0%D0%B1%D0%B6%D0%B5%D0%BD%D0%B8%D1%8F,%20...-626x417.jpeg","A2phQUvu+i82jKUoXZQskg==":"%D0%9C%D0%B5%D0%BB%D0%B8%D0%BE%D1%80%D0%B0%D1%86%D0%B8%D1%8F,%20%D1%80%D0%B5%D0%BA%D1%83%D0%BB%D1%8C%D1%82%D0%B8%D0%B2%D0%B0%D1%86%D0%B8%D1%8F%20%D0%B8%20%D0%BE%D1%85%D1%80%D0%B0%D0%BD%D0%B0%20%D0%B7%D0%B5%D0%BC%D0%B5%D0%BB%D1%8C-400x267.jpeg","6c3LUa3GCuNobzDMIkhikQ==":"%D0%9A%D0%BE%D0%BC%D0%BF%D0%BB%D0%B5%D0%BA%D1%81%D0%BD%D0%BE%D0%B5%20%D0%B8%D1%81%D0%BF%D0%BE%D0%BB%D1%8C%D0%B7%D0%BE%D0%B2%D0%B0%D0%BD%D0%B8%D0%B5%20%D0%B8%20%D0%BE%D1%85%D1%80%D0%B0%D0%BD%D0%B0%20%D0%B2%D0%BE%D0%B4%D0%BD%D1%8B%D1%85%20%D1%80%D0%B5%D1%81%D1%83%D1%80%D1%81%D0%BE%D0%B2.webp","SlV47JOk/i97IwKpOM6wVw==":"%D0%9C%D0%B5%D0%B4%D0%B8%D0%BA%D0%BE-%D0%BF%D1%80%D0%BE%D1%84%D0%B8%D0%BB%D0%B0%D0%BA%D1%82%D0%B8%D1%87%D0%B5%D1%81%D0%BA%D0%BE%D0%B5%20%D0%B4%D0%B5%D0%BB%D0%BE-626x391.jpeg","0Z4Gg2PPH5cz8QZ1lY7Obw==":"farma-626x417.jpeg","z02L7+p72NTouqmuL8734w==":"%D0%9F%D0%B5%D0%B4%D0%B8%D0%B0%D1%82%D1%80%D0%B8%D1%8F-626x417.jpeg","/nUPm9pymDiVsn6QeXCv0g==":"_%D0%9B%D0%B5%D1%87%D0%B5%D0%B1%D0%BD%D0%BE%D0%B5%20%D0%B4%D0%B5%D0%BB%D0%BE-626x438.jpeg","fLE/EiUNZ3Nak6WwGw4TSA==":"%D0%A1%D1%82%D0%BE%D0%BC%D0%B0%D1%82%D0%BE%D0%BB%D0%BE%D0%B3%D0%B8%D1%8F-626x352.jpeg","VrObTrmcFtTsHIyilKdfEg==":"%D0%A1%D0%BE%D0%B2%D1%80%D0%B5%D0%BC%D0%B5%D0%BD%D0%BD%D1%8B%D0%B5%20%D1%82%D0%B5%D1%85%D0%BD%D0%BE%D0%BB%D0%BE%D0%B3%D0%B8%D0%B8%20%D0%BF%D0%B5%D1%80%D0%B5%D1%80%D0%B0%D0%B1%D0%BE%D1%82%D0%BA%D0%B8%20%D1%80%D0%B0%D1%81%D1%82%D0%B8%D1%82%D0%B5%D0%BB%D1%8C%D0%BD%D0%BE%D0%B3%D0%BE%20%D1%81%D1%8B%D1%80%D1%8C%D1%8F-626x352.jpeg","ox/A801NWSCMmXrhJJk25g==":"%D0%98%D0%BD%D1%84%D0%BE%D1%80%D0%BC%D0%B0%D1%86%D0%B8%D0%BE%D0%BD%D0%BD%D0%BE-%D0%B8%D0%B7%D0%BC%D0%B5%D1%80%D0%B8%D1%82%D0%B5%D0%BB%D1%8C%D0%BD%D0%B0%D1%8F%20%D1%82%D0%B5%D1%85%D0%BD%D0%B8%D0%BA%D0%B0%20%D0%B8%20%D1%82%D0%B5%D1%85%D0%BD%D0%BE%D0%BB%D0%BE%D0%B3%D0%B8%D0%B8-626x348.jpg","D+W2QDqmoFF5PjYhoptXNg==":"%D0%9A%D0%BE%D0%BD%D1%81%D1%82%D1%80%D1%83%D0%B8%D1%80%D0%BE%D0%B2%D0%B0%D0%BD%D0%B8%D0%B5%20%D1%88%D0%B2%D0%B5%D0%B9%D0%BD%D1%8B%D1%85%20%D0%B8%D0%B7%D0%B4%D0%B5%D0%BB%D0%B8%D0%B9-626x417.jpeg","6WwhXa+tIvdxLJdb+FfOqg==":"%D0%9C%D0%B0%D1%88%D0%B8%D0%BD%D1%8B%20%D0%B8%20%D0%B0%D0%BF%D0%BF%D0%B0%D1%80%D0%B0%D1%82%D1%8B%20%D0%BF%D0%B8%D1%89%D0%B5%D0%B2%D1%8B%D1%85%20%D0%BF%D1%80%D0%BE%D0%B8%D0%B7%D0%B2%D0%BE%D0%B4%D1%81%D1%82%D0%B2-626x404.jpeg","JRWjgLjVel/Bl6PVEb1UUg==":"home-122x122.jpg","k+oapQ7In77xvR0w3mIkqw==":"home-122x122.jpeg","woVUQSbzYzq7GuUtH2D92w==":"mbr-122x122.jpg","6JTVO1vOoqKxGzphSDcO/g==":"1-1440x900.jpg","uYe2PRNORqj39FWwv8+Lww==":"2-2000x1676.jpg","mv8WZX/jwG8o78YH89CrSw==":"2.webp","7VNWjTc2BwIF+3g4btWS0g==":"3-2000x1331.jpg","Q1z3CzlfrUMJWUPrwQrj9A==":"5-1920x1200.jpg","rp1LPT+rLGAC1ZCSZO6Kfw==":"6-1400x1050.jpg","KXpJFpgx+GeM56v9Q/fJ1A==":"7-1500x1125.jpg","ZCBCL3m5wiDPobUXMS6GDA==":"8-1200x800.jpg","1Dc5VRibN3szZOSoWByJnA==":"2-2000x1676.jpeg","WqZ184k/Ve9oa0uICN5PYw==":"1-1440x900.jpeg","eXXLgQ+4vLTqxjpYh7JNqA==":"2-1.webp","Jj3VCt2kp8h/Di1MfXO66g==":"3-2000x1331.jpeg","Vo39jrl7dt5szLNcNAxBQA==":"6-1400x1050.jpeg","//Vp/5T5oIcag0FH/rl/ow==":"8-1200x800.jpeg","TltlCNREuODsJznYn2i9Vg==":"7-1500x1125.jpeg","6YSdnTSvotHPqyWUj9ij0g==":"5-1920x1200.jpeg","pgUD1dOqmFaLylrcbVh4Ng==":"mbr-122x122.png","FrsNSzZ6cnuhtitFWYWG3g==":"orig-96x96.jpeg","hLSPI5CTvvDloNjFq0d5cg==":"home-96x96.jpg","dNn/Ma7Q8g0Au0x2DFmWkA==":"%D0%9F%D1%80%D0%B0%D0%B2%D0%BE%D0%B2%D0%BE%D0%B5%20%D0%BE%D0%B1%D0%B5%D1%81%D0%BF%D0%B5%D1%87%D0%B5%D0%BD%D0%B8%D0%B5%20%D0%BD%D0%B0%D1%86%D0%B8%D0%BE%D0%BD%D0%B0%D0%BB%D1%8C%D0%BD%D0%BE%D0%B9%20%D0%B1%D0%B5%D0%B7%D0%BE%D0%BF%D0%B0%D1%81%D0%BD%D0%BE%D1%81%D1%82%D0%B8-1046x785.jpeg","hpYC0RLVDhaj6o8sQ7DuaA==":"%D0%A4%D0%B8%D0%B7%D0%B8%D1%87%D0%B5%D1%81%D0%BA%D0%B0%D1%8F%20%D0%BA%D1%83%D0%BB%D1%8C%D1%82%D1%83%D1%80%D0%B0%20%D0%B8%20%D0%B1%D0%B5%D0%B7%D0%BE%D0%BF%D0%B0%D1%81%D0%BD%D0%BE%D1%81%D1%82%D1%8C%20%D0%B6%D0%B8%D0%B7%D0%BD%D0%B5%D0%B4%D0%B5%D1%8F%D1%82%D0%B5%D0%BB%D1%8C%D0%BD%D0%BE%D1%81%D1%82%D0%B8-960x720.jpeg","JUZ5xt35G3Ua+u2HSQRDig==":"%D0%9F%D1%81%D0%B8%D1%85%D0%BE%D0%BB%D0%BE%D0%B3%D0%B8%D1%8F%20%D1%83%D0%BF%D1%80%D0%B0%D0%B2%D0%BB%D0%B5%D0%BD%D0%B8%D1%8F-1024x784.jpeg","WxcrlJn5qV6q213Fsykq2A==":"%D0%91%D1%83%D1%85%D0%B3%D0%B0%D0%BB%D1%82%D0%B5%D1%80%D1%81%D0%BA%D0%B8%D0%B9%20%D1%83%D1%87%D0%B5%D1%82,%20%D0%B0%D0%BD%D0%B0%D0%BB%D0%B8%D0%B7%20%D0%B8%20%D0%B0%D1%83%D0%B4%D0%B8%D1%82-1023x559.jpeg","FT9IzYBqTk1FOznjmdaR6g==":"%D0%98%D0%BD%D1%82%D0%B5%D1%80%D0%BD%D0%B5%D1%82%20%D0%BA%D0%BE%D0%BC%D0%BC%D1%83%D0%BD%D0%B8%D0%BA%D0%B0%D1%86%D0%B8%D0%B8%20%D0%B8%20web-%D0%B4%D0%B8%D0%B7%D0%B0%D0%B9%D0%BD-1046x588.jpeg","82jIHJ7VGvLQX1F++NNF5g==":"%D0%93%D0%BE%D1%81%D1%83%D0%B4%D0%B0%D1%80%D1%81%D1%82%D0%B2%D0%B5%D0%BD%D0%BD%D0%BE%D0%B5%20%D0%B8%20%D0%BC%D1%83%D0%BD%D0%B8%D1%86%D0%B8%D0%BF%D0%B0%D0%BB%D1%8C%D0%BD%D0%BE%D0%B5%20%D1%83%D0%BF%D1%80%D0%B0%D0%B2%D0%BB%D0%B5%D0%BD%D0%B8%D0%B5-1046x697.jpeg","NOTGxEqHEKrT9ui8sOni3w==":"%D0%9F%D1%81%D0%B8%D1%85%D0%BE%D0%BB%D0%BE%D0%B3%D0%B8%D1%8F%20%D1%83%D0%BF%D1%80%D0%B0%D0%B2%D0%BB%D0%B5%D0%BD%D0%B8%D1%8F-1024x784.jpg"}